.hgignore
.project
.pydevproject
LICENSE
MANIFEST.in
README.txt
bootstrap.py
buildout.cfg
setup.py
bin/buildout
docs/HISTORY.txt
docs/README.txt
src/ztfy/__init__.py
src/ztfy.file.egg-info/PKG-INFO
src/ztfy.file.egg-info/SOURCES.txt
src/ztfy.file.egg-info/dependency_links.txt
src/ztfy.file.egg-info/entry_points.txt
src/ztfy.file.egg-info/namespace_packages.txt
src/ztfy.file.egg-info/not-zip-safe
src/ztfy.file.egg-info/requires.txt
src/ztfy.file.egg-info/top_level.txt
src/ztfy/file/README.txt
src/ztfy/file/__init__.py
src/ztfy/file/adapter.py
src/ztfy/file/configure.zcml
src/ztfy/file/display.py
src/ztfy/file/events.py
src/ztfy/file/image.py
src/ztfy/file/interfaces.py
src/ztfy/file/pil.py
src/ztfy/file/property.py
src/ztfy/file/schema.py
src/ztfy/file/vocabulary.py
src/ztfy/file/archive/__init__.py
src/ztfy/file/archive/bz2.py
src/ztfy/file/archive/configure.zcml
src/ztfy/file/archive/gz.py
src/ztfy/file/archive/tar.py
src/ztfy/file/archive/zip.py
src/ztfy/file/browser/__init__.py
src/ztfy/file/browser/configure.zcml
src/ztfy/file/browser/namespace.py
src/ztfy/file/browser/resources/js/ztfy.file.js
src/ztfy/file/browser/resources/js/ztfy.file.min.js
src/ztfy/file/browser/widget/__init__.py
src/ztfy/file/browser/widget/configure.zcml
src/ztfy/file/browser/widget/converter.py
src/ztfy/file/browser/widget/interfaces.py
src/ztfy/file/browser/widget/templates/cthumb_display.pt
src/ztfy/file/browser/widget/templates/cthumb_input.pt
src/ztfy/file/browser/widget/templates/file_display.pt
src/ztfy/file/browser/widget/templates/file_input.pt
src/ztfy/file/browser/widget/templates/html_display.pt
src/ztfy/file/browser/widget/templates/html_input.pt
src/ztfy/file/browser/widget/templates/image_display.pt
src/ztfy/file/browser/widget/templates/image_input.pt
src/ztfy/file/doctests/README.txt
src/ztfy/file/doctests/TFNA0908-D7.05726.jpg
src/ztfy/file/locales/ztfy.file.pot
src/ztfy/file/locales/en/LC_MESSAGES/ztfy.file.mo
src/ztfy/file/locales/en/LC_MESSAGES/ztfy.file.po
src/ztfy/file/locales/fr/LC_MESSAGES/ztfy.file.mo
src/ztfy/file/locales/fr/LC_MESSAGES/ztfy.file.po
src/ztfy/file/magic/mime.types
src/ztfy/file/tal/__init__.py
src/ztfy/file/tal/api.py
src/ztfy/file/tal/configure.zcml
src/ztfy/file/tal/interfaces.py
src/ztfy/file/tests/__init__.py
